{
  "main": {
    "id": "88b630e7fe654874",
    "type": "split",
    "children": [
      {
        "id": "c273712d97a63b63",
        "type": "tabs",
        "children": [
          {
            "id": "7735953cd4d54ec6",
            "type": "leaf",
            "state": {
              "type": "markdown",
              "state": {
                "file": "University/Closure of a set.md",
                "mode": "source",
                "backlinks": false,
                "source": false
              }
            }
          },
          {
            "id": "f5d297a74c6212ab",
            "type": "leaf",
            "state": {
              "type": "markdown",
              "state": {
                "file": "University/Properties of Topology on Metric Spaces.md",
                "mode": "preview",
                "backlinks": false,
                "source": false
              }
            }
          },
          {
            "id": "aafb6cf669ae3765",
            "type": "leaf",
            "state": {
              "type": "markdown",
              "state": {
                "file": "University/Semester 1/Metric Spaces/Metric Spaces Lectures/Metric Spaces - MAT00037H Lectures.md",
                "mode": "preview",
                "backlinks": false,
                "source": false
              }
            }
          }
        ]
      },
      {
        "id": "cc581682ceb59119",
        "type": "tabs",
        "children": [
          {
            "id": "b236aaf719c2f541",
            "type": "leaf",
            "state": {
              "type": "excalidraw",
              "state": {
                "file": "University/Semester 1/Metric Spaces/Metric Spaces Lectures/Metric Space Lecture 5 part 2.md"
              }
            }
          },
          {
            "id": "8b40c7373edf3ce3",
            "type": "leaf",
            "state": {
              "type": "excalidraw",
              "state": {
                "file": "University/Semester 1/Metric Spaces/Metric Spaces Lectures/Metric Spaces Lecture 6.md"
              }
            }
          }
        ],
        "currentTab": 1
      }
    ],
    "direction": "vertical"
  },
  "left": {
    "id": "d2b7029fdadb1d50",
    "type": "split",
    "children": [
      {
        "id": "46bb046e83d884a3",
        "type": "tabs",
        "children": [
          {
            "id": "3fb07fabad84e87c",
            "type": "leaf",
            "state": {
              "type": "file-explorer",
              "state": {
                "sortOrder": "alphabetical"
              }
            }
          },
          {
            "id": "272f77912fb31de6",
            "type": "leaf",
            "state": {
              "type": "search",
              "state": {
                "query": "",
                "matchingCase": false,
                "explainSearch": false,
                "collapseAll": false,
                "extraContext": false,
                "sortOrder": "alphabetical"
              }
            }
          },
          {
            "id": "ccb609962f10db7d",
            "type": "leaf",
            "state": {
              "type": "bookmarks",
              "state": {}
            }
          },
          {
            "id": "a5406c0ed6d42b90",
            "type": "leaf",
            "state": {
              "type": "mk-file-view",
              "state": {}
            }
          }
        ]
      }
    ],
    "direction": "horizontal",
    "width": 567,
    "collapsed": true
  },
  "right": {
    "id": "49fd56b1e1b75feb",
    "type": "split",
    "children": [
      {
        "id": "788d8fba795006da",
        "type": "tabs",
        "children": [
          {
            "id": "3d77320463417f99",
            "type": "leaf",
            "state": {
              "type": "google-calendar-view-month",
              "state": {}
            }
          },
          {
            "id": "0f3a44cd9f21b602",
            "type": "leaf",
            "state": {
              "type": "googleTaskView",
              "state": {}
            }
          },
          {
            "id": "8833707e6daf7dc3",
            "type": "leaf",
            "state": {
              "type": "backlink",
              "state": {
                "file": "University/Closure of a set.md",
                "collapseAll": false,
                "extraContext": false,
                "sortOrder": "alphabetical",
                "showSearch": false,
                "searchQuery": "",
                "backlinkCollapsed": false,
                "unlinkedCollapsed": true
              }
            }
          },
          {
            "id": "7093d4610bcfe0d4",
            "type": "leaf",
            "state": {
              "type": "outgoing-link",
              "state": {
                "file": "University/Closure of a set.md",
                "linksCollapsed": false,
                "unlinkedCollapsed": true
              }
            }
          },
          {
            "id": "5d2c84650ac0b6aa",
            "type": "leaf",
            "state": {
              "type": "tag",
              "state": {
                "sortOrder": "frequency",
                "useHierarchy": true
              }
            }
          },
          {
            "id": "2b502af48ca87f64",
            "type": "leaf",
            "state": {
              "type": "outline",
              "state": {
                "file": "University/Closure of a set.md"
              }
            }
          },
          {
            "id": "0fda624a831477ca",
            "type": "leaf",
            "state": {
              "type": "advanced-tables-toolbar",
              "state": {}
            }
          },
          {
            "id": "4630adab8fc7babd",
            "type": "leaf",
            "state": {
              "type": "calendar",
              "state": {}
            }
          },
          {
            "id": "e5272453c6f304dd",
            "type": "leaf",
            "state": {
              "type": "online.larslockefeer.obsidian-plugin-todo",
              "state": {}
            }
          },
          {
            "id": "4059327e9b97792f",
            "type": "leaf",
            "state": {
              "type": "all-properties",
              "state": {
                "sortOrder": "frequency"
              }
            }
          }
        ],
        "currentTab": 1
      }
    ],
    "direction": "horizontal",
    "width": 379,
    "collapsed": true
  },
  "left-ribbon": {
    "hiddenItems": {
      "homepage:Open homepage": false,
      "graph:Open graph view": false,
      "switcher:Open quick switcher": false,
      "canvas:Create new canvas": false,
      "daily-notes:Open today's daily note": false,
      "templates:Insert template": false,
      "command-palette:Open command palette": false,
      "3d-graph:3D Graph": false,
      "table-editor-obsidian:Advanced Tables Toolbar": false,
      "dbfolder:Create a new database table": false,
      "obsidian-excalidraw-plugin:Create new drawing": false,
      "obsidian-full-calendar:Open Full Calendar": false,
      "terminal:Open terminal": false,
      "templater-obsidian:Templater": false,
      "sync-google-calendar:Sync Google Calendar": false,
      "obsidian-matrix:Obsidian Matrix": false,
      "workspaces:Manage workspace layouts": false,
      "periodic-notes:Open today": false,
      "obsidian-google-tasks:Google Tasks": false
    }
  },
  "active": "7735953cd4d54ec6",
  "lastOpenFiles": [
    "University/The (basic) Geometry of Metric Spaces.md",
    "University/Closure of a set.md",
    "University/Properties of Topology on Metric Spaces.md",
    "University/Semester 1/Metric Spaces/Metric Spaces - MAT00037H Outline.md",
    "University/Topology on Metric Spaces.md",
    "University/Collections of Closed Sets.md",
    "University/Open and Closed Sets.md",
    "HOME.md",
    "University/Semester 1/Metric Spaces/Metric Spaces Lectures/Metric Spaces - MAT00037H Lectures.md",
    "University/Properties off Center of Mass.md",
    "University/Definition of Topology on Metric Spaces.md",
    "University/Semester 1/Metric Spaces/Metric Spaces Lectures/Metric Spaces Lecture 6.md",
    "University/Semester 1/Metric Spaces/Metric Spaces Lectures/Metric Space Lecture 5 part 2.md",
    "University/Semester 1/Metric Spaces/Metric Spaces - MAT00037H.md",
    "University/Open Set as Union of Open Balls.md",
    "University/Open Ball is an Open Set.md",
    "University/Describing Open Sets using Interior Points.md",
    "University/Interior and Exterior and Boundary Points.md",
    "University/Relation between Open and Closed Sets.md",
    "University/Open and Closed Balls.md",
    "University/Open Balls in Analysis.md",
    "Excalidraw/Drawing 2023-10-19 16.18.29_0.excalidraw.md",
    "University/Open Ball is Open Set Proof light.svg",
    "University/Open Ball is Open Set proof dark.svg",
    "Excalidraw/Drawing 2023-10-02 13.32.35.excalidraw.md",
    "Excalidraw/Drawing 2023-10-07 22.51.14.excalidraw.md",
    "Excalidraw/Drawing 2023-10-12 16.02.24.excalidraw.md",
    "Excalidraw/Drawing 2023-10-12 16.02.25.excalidraw.md",
    "University/Untitled Diagram.svg",
    "University/subspace.svg",
    "Vector calculus assignment 1.pdf",
    "University/Semester 1/Vector & Complex Calculus/Problem Sheets/Solutions/Vector calculus assignment 1.pdf",
    "Images/space_saturn.png",
    "University/Semester 1/Vector & Complex Calculus/Problem Sheets/vcex-1-2023-24.pdf",
    "University/Semester 1/Vector & Complex Calculus/Problem Sheets/VC-EX-2023-24-FC.pdf",
    "University/Semester 1/Vector & Complex Calculus/Problem Sheets/Solutions",
    "University/Semester 1/Vector & Complex Calculus/Problem Sheets/Assignments",
    "University/Semester 1/Vector & Complex Calculus/Problem Sheets",
    "University/Semester 1/Metric Spaces/Problem Sheets/Solutions",
    "University/Semester 1/Metric Spaces/Problem Sheets/Assignments",
    "University/Semester 1/Metric Spaces/Problem Sheets",
    "home.jpg",
    "Images/ken-cheung-KonWFWUaAuk-unsplash.jpg",
    "University/Open Sets Diagram.svg",
    "University/Pasted image 20230927163933.png",
    "University/Pasted image 20230929191527.png",
    "Untitled.canvas",
    "Untitled 1.canvas"
  ]
}